odoo/addons/account_statement_import_camt/README.rst
odoo/addons/account_statement_import_camt/__init__.py
odoo/addons/account_statement_import_camt/__manifest__.py
odoo/addons/account_statement_import_camt/i18n/account_statement_import_camt.pot
odoo/addons/account_statement_import_camt/i18n/ca.po
odoo/addons/account_statement_import_camt/i18n/de.po
odoo/addons/account_statement_import_camt/i18n/es.po
odoo/addons/account_statement_import_camt/i18n/fa.po
odoo/addons/account_statement_import_camt/i18n/fi.po
odoo/addons/account_statement_import_camt/i18n/fr.po
odoo/addons/account_statement_import_camt/i18n/fr_CH.po
odoo/addons/account_statement_import_camt/i18n/gl.po
odoo/addons/account_statement_import_camt/i18n/hr.po
odoo/addons/account_statement_import_camt/i18n/it.po
odoo/addons/account_statement_import_camt/i18n/lt_LT.po
odoo/addons/account_statement_import_camt/i18n/nb_NO.po
odoo/addons/account_statement_import_camt/i18n/nl.po
odoo/addons/account_statement_import_camt/i18n/pt_BR.po
odoo/addons/account_statement_import_camt/i18n/pt_PT.po
odoo/addons/account_statement_import_camt/i18n/sl.po
odoo/addons/account_statement_import_camt/models/__init__.py
odoo/addons/account_statement_import_camt/models/account_bank_statement_line.py
odoo/addons/account_statement_import_camt/models/account_journal.py
odoo/addons/account_statement_import_camt/models/account_statement_import.py
odoo/addons/account_statement_import_camt/models/bank_statement.py
odoo/addons/account_statement_import_camt/models/parser.py
odoo/addons/account_statement_import_camt/readme/CONTRIBUTORS.rst
odoo/addons/account_statement_import_camt/readme/DESCRIPTION.rst
odoo/addons/account_statement_import_camt/readme/newsfragment/1_verbose_narration.feature
odoo/addons/account_statement_import_camt/static/description/icon.png
odoo/addons/account_statement_import_camt/static/description/index.html
odoo/addons/account_statement_import_camt/test_files/golden-camt053-no-ntry.pydata
odoo14_addon_account_statement_import_camt-14.0.1.2.1.dist-info/METADATA
odoo14_addon_account_statement_import_camt-14.0.1.2.1.dist-info/WHEEL
odoo14_addon_account_statement_import_camt-14.0.1.2.1.dist-info/top_level.txt
odoo14_addon_account_statement_import_camt-14.0.1.2.1.dist-info/RECORD
